{
  "last_update_id": 261520107,
  "awaiting_amount": {},
  "last_request_at": {
    "5503157793": 1783626661.828241,
    "8617443875": 1783371828.391422,
    "6671003365": 1783444699.2751603,
    "6458834875": 1783497978.5755217,
    "7356289290": 1783510245.2560897,
    "5396728087": 1783498082.384285,
    "8658029962": 1783517185.8056793,
    "1499517373": 1783540927.5702777,
    "7113359067": 1783583534.9440913,
    "8602259176": 1783632690.3335621
  },
  "rate_cache": {
    "fetched_at": 1783371829.333584,
    "snapshot": {
      "buy": {
        "platform": "Bybit",
        "trade_type": "BUY",
        "price": 1340.0,
        "merchant_name": "Yomicash ",
        "completion_rate": 1.0,
        "order_count": 29,
        "min_limit": 50000.0,
        "max_limit": 64320.0,
        "available": 48.0,
        "payment_methods": [],
        "adv_no": "2067732602720227328",
        "link": "https://www.bybit.com/fiat/trade/otc"
      },
      "sell": {
        "platform": "Bybit",
        "trade_type": "SELL",
        "price": 1504.0,
        "merchant_name": "GoldenPrimeEx",
        "completion_rate": 0.99,
        "order_count": 1106,
        "min_limit": 5000.0,
        "max_limit": 700000.0,
        "available": 50000.0,
        "payment_methods": [],
        "adv_no": "2050799808397766656",
        "link": "https://www.bybit.com/fiat/trade/otc"
      }
    },
    "NGN": {
      "fetched_at": 1783701106.7512708,
      "snapshot": {
        "buy": {
          "platform": "Bybit",
          "trade_type": "BUY",
          "fiat": "NGN",
          "price": 1340.0,
          "merchant_name": "Yomicash ",
          "completion_rate": 1.0,
          "order_count": 28,
          "min_limit": 50000.0,
          "max_limit": 64320.0,
          "available": 48.0,
          "payment_methods": [],
          "adv_no": "2067732602720227328",
          "link": "https://www.bybit.com/fiat/trade/otc"
        },
        "sell": {
          "platform": "Bybit",
          "trade_type": "SELL",
          "fiat": "NGN",
          "price": 1396.51,
          "merchant_name": "Mary\ud83e\udd8b",
          "completion_rate": 0.95,
          "order_count": 104,
          "min_limit": 11850.0,
          "max_limit": 50500.0,
          "available": 251.0,
          "payment_methods": [],
          "adv_no": "2071550643147853824",
          "link": "https://www.bybit.com/fiat/trade/otc"
        }
      }
    },
    "EUR": {
      "fetched_at": 1783701111.3385906,
      "snapshot": {
        "buy": {
          "platform": "Bybit",
          "trade_type": "BUY",
          "fiat": "EUR",
          "price": 0.874,
          "merchant_name": "bestchange.kh",
          "completion_rate": 0.99,
          "order_count": 1218,
          "min_limit": 25.0,
          "max_limit": 2227.621,
          "available": 2548.7658,
          "payment_methods": [],
          "adv_no": "1944632819764613120",
          "link": "https://www.bybit.com/fiat/trade/otc"
        },
        "sell": {
          "platform": "Bybit",
          "trade_type": "SELL",
          "fiat": "EUR",
          "price": 1.048,
          "merchant_name": "MikeSwift",
          "completion_rate": 0.96,
          "order_count": 24,
          "min_limit": 50.0,
          "max_limit": 250.0,
          "available": 19775.0,
          "payment_methods": [],
          "adv_no": "2067894679335477248",
          "link": "https://www.bybit.com/fiat/trade/otc"
        }
      }
    },
    "JPY": {
      "fetched_at": 1783701107.9237058,
      "snapshot": {
        "buy": {
          "platform": "Binance",
          "trade_type": "BUY",
          "fiat": "JPY",
          "price": 183.8,
          "merchant_name": "LNLJP",
          "completion_rate": 1.0,
          "order_count": 219,
          "min_limit": 4500.0,
          "max_limit": 200000.0,
          "available": 202.89,
          "payment_methods": [
            "PayPay Money"
          ],
          "adv_no": "12889634815195684864",
          "link": "https://c2c.binance.com/en/adv?code=12889634815195684864"
        },
        "sell": {
          "platform": "Binance",
          "trade_type": "SELL",
          "fiat": "JPY",
          "price": 161.55,
          "merchant_name": "PK_CRYPTO_PRO2026",
          "completion_rate": 0.984,
          "order_count": 293,
          "min_limit": 500.0,
          "max_limit": 100000.0,
          "available": 155.81,
          "payment_methods": [
            "PayPay Money"
          ],
          "adv_no": "12835504579111698432",
          "link": "https://c2c.binance.com/en/adv?code=12835504579111698432"
        }
      }
    },
    "CHF": {
      "fetched_at": 1783701108.9614227,
      "snapshot": {
        "buy": {
          "platform": "Binance",
          "trade_type": "BUY",
          "fiat": "CHF",
          "price": 0.939,
          "merchant_name": "Best_Twint_Exchange",
          "completion_rate": 0.996,
          "order_count": 205,
          "min_limit": 5.0,
          "max_limit": 3000.0,
          "available": 10738.41,
          "payment_methods": [
            "Instant Transfer",
            "Bank Transfer",
            "Cash Deposit to Bank",
            "Twint"
          ],
          "adv_no": "13894664478762012672",
          "link": "https://c2c.binance.com/en/adv?code=13894664478762012672"
        },
        "sell": {
          "platform": "Binance",
          "trade_type": "SELL",
          "fiat": "CHF",
          "price": 0.81,
          "merchant_name": "dejuredefacto",
          "completion_rate": 0.958,
          "order_count": 67,
          "min_limit": 50.0,
          "max_limit": 297.0,
          "available": 366.67,
          "payment_methods": [
            "Twint"
          ],
          "adv_no": "12901307694961897472",
          "link": "https://c2c.binance.com/en/adv?code=12901307694961897472"
        }
      }
    },
    "GBP": {
      "fetched_at": 1783701110.0961785,
      "snapshot": {
        "buy": {
          "platform": "Binance",
          "trade_type": "BUY",
          "fiat": "GBP",
          "price": 0.77,
          "merchant_name": "FastEchangeTrading",
          "completion_rate": 1.0,
          "order_count": 42,
          "min_limit": 10.0,
          "max_limit": 5000.0,
          "available": 83.6,
          "payment_methods": [
            "Alipay"
          ],
          "adv_no": "12907037409809637376",
          "link": "https://c2c.binance.com/en/adv?code=12907037409809637376"
        },
        "sell": {
          "platform": "Bybit",
          "trade_type": "SELL",
          "fiat": "GBP",
          "price": 0.894,
          "merchant_name": "billtoken",
          "completion_rate": 0.95,
          "order_count": 68,
          "min_limit": 30.0,
          "max_limit": 217.0,
          "available": 19268.9768,
          "payment_methods": [],
          "adv_no": "2065420699327389696",
          "link": "https://www.bybit.com/fiat/trade/otc"
        }
      }
    },
    "USD": {
      "fetched_at": 1783701112.5655859,
      "snapshot": {
        "buy": {
          "platform": "Bybit",
          "trade_type": "BUY",
          "fiat": "USD",
          "price": 0.8,
          "merchant_name": "DagestanDentist",
          "completion_rate": 1.0,
          "order_count": 188,
          "min_limit": 50.0,
          "max_limit": 1853.2,
          "available": 2316.5,
          "payment_methods": [],
          "adv_no": "1768869022963105792",
          "link": "https://www.bybit.com/fiat/trade/otc"
        },
        "sell": {
          "platform": "Bybit",
          "trade_type": "SELL",
          "fiat": "USD",
          "price": 1.2,
          "merchant_name": "\ud835\udd3b\ud835\udd60\ud835\udd5f\ud835\udd56_\ud835\udd4f\ud835\udd54\ud835\udd59\ud835\udd52\ud835\udd5f\ud835\udd58\ud835\udd56\ud83c\udf1f",
          "completion_rate": 1.0,
          "order_count": 694,
          "min_limit": 10.0,
          "max_limit": 22138.791,
          "available": 18448.9929,
          "payment_methods": [],
          "adv_no": "2013559487527952384",
          "link": "https://www.bybit.com/fiat/trade/otc"
        }
      }
    }
  },
  "consecutive_poll_failures": 0,
  "awaiting_admin_action": {}
}